{
  "name": "TableRowCollection",
  "description": "Represents a collection of all the rows that are part of the table.",
  "isCollection": true,
  "collectionOf": "TableRow",
  "restPath": null,
  "info": {
    "version": "1.1",
    "reqSet": "1.1",
    "addinTypes": [
      "Excel"
    ],
    "nameSpace": "Excel",
    "addinHosts": [
      "Task pane"
    ],
    "title": "Office JavaScript Add-in API",
    "description": "Office JavaScript Add-in API"
  },
  "properties": [
    {
      "name": "count",
      "dataType": "int",
      "description": "Returns the number of rows in the table.",
      "isReadOnly": true,
      "enumNameJs": null,
      "isCollection": false,
      "isRelationship": false,
      "reqSet": "1.1",
      "isKey": null,
      "notes": null
    },
    {
      "name": "items",
      "dataType": "TableRow[]",
      "description": "A collection of tableRow objects.",
      "isReadOnly": true,
      "enumNameJs": null,
      "isCollection": true,
      "isRelationship": false,
      "reqSet": "1.1",
      "isKey": null,
      "notes": null
    }
  ],
  "methods": [
    {
      "name": "getCount",
      "returnType": "int",
      "description": "Gets the number of rows in the table.",
      "syntax": "tableRowCollectionObject.getCount();",
      "signature": "getCount()",
      "restfulName": "Count",
      "notes": null,
      "httpSuccessResponse": null,
      "parameters": null,
      "reqSet": "1.4"
    },
    {
      "name": "getItemAt",
      "returnType": "TableRow",
      "description": "Gets a row based on its position in the collection.",
      "syntax": "tableRowCollectionObject.getItemAt(index);",
      "signature": "getItemAt(index: number)",
      "restfulName": "ItemAt",
      "notes": null,
      "httpSuccessResponse": null,
      "parameters": [
        {
          "name": "index",
          "dataType": "number",
          "isCollection": false,
          "description": "Index value of the object to be retrieved. Zero-indexed.",
          "isRequired": true,
          "enumNameJs": null,
          "notes": null
        }
      ],
      "reqSet": "1.1"
    },
    {
      "name": "add",
      "returnType": "TableRow",
      "description": "Adds one or more rows to the table. The return object will be the top of the newly added row(s).",
      "syntax": "tableRowCollectionObject.add(index, values);",
      "signature": "add(index: number, values: object)",
      "restfulName": "add",
      "notes": null,
      "httpSuccessResponse": null,
      "parameters": [
        {
          "name": "index",
          "dataType": "number",
          "isCollection": false,
          "description": "Specifies the relative position of the new row. If null or -1, the addition happens at the end. Any rows below the inserted row are shifted downwards. Zero-indexed.",
          "isRequired": false,
          "enumNameJs": null,
          "notes": null
        },
        {
          "name": "values",
          "dataType": "object",
          "isCollection": false,
          "description": "A 2-dimensional array of unformatted values of the table row.",
          "isRequired": false,
          "enumNameJs": null,
          "notes": null
        }
      ],
      "reqSet": "1.1"
    }
  ]
}